<?xml version="1.0" encoding="windows-1250" ?>
<!--


#include "h1200_typeid.h"
#include "h1220_pictureid.h"
#include "h1250_raport_macros.h"
#include "h1206_pit_form_macros.h"

#define X_PICTURE_WIDTH			19700
#define Y_PICTURE_HEIGHT		28000


' NIP
#define X_POLE1A X_S_OFFSET_PT5L + 500
#define Y_POLE1A Y_S_F_T_OFFSET_PT5L + 600

#define X_POLE1B X_POLE1A + 1800
#define Y_POLE1B Y_POLE1A

#define X_POLE1C X_POLE1B + 1900
#define Y_POLE1C Y_POLE1A

#define X_POLE1D X_POLE1C + 1300
#define Y_POLE1D Y_POLE1A




' miesiąc i rok
#define Y_DATA_OFFSET 3150
' miesiąc (POLE 4)
#define X_POLE4A X_STD_POLE_PT5L + 4100
#define Y_POLE4A Y_DATA_OFFSET + Y_S_F_T_OFFSET_PT5L
' rok (POLE 5)
#define X_POLE4B X_STD_POLE_PT5L + 5550
#define Y_POLE4B Y_DATA_OFFSET + Y_S_F_T_OFFSET_PT5L



' Urząd skarbowy (POLE 6)
' Odległość sekcji "A" od początku kartki
#define Y_SA_OFFSET  7500
#define Y_SA_H 1700
#define Y_POLE5 Y_SA_OFFSET + Y_S_F_OFFSET_PT5L + Y_S_F_T_OFFSET_PT5L
#define X_POLE5 X_STD_POLE_PT5L


' sekcja "B"

#define Y_SB_OFFSET  Y_SA_OFFSET + Y_SA_H
'wysokosc sekcji B
#define Y_SB_H 6800

' pole 6
#define X_POLE6 X_STD_POLE_PT5L
#define Y_POLE6 Y_SB_OFFSET + 1500 + Y_S_F_T_OFFSET_PT5L

' pole 7
#define X_POLE7 X_STD_POLE_PT5L
#define Y_POLE7 Y_POLE6 + Y_F_H_PT5L

'pole 8 - data urodzenia
'dzien
#define X_POLE8A X_POLE7 + 13800
#define Y_POLE8A Y_POLE7
' miesiąc 
#define X_POLE8B X_POLE8A + 1200
#define Y_POLE8B Y_POLE8A
' rok 
#define X_POLE8C X_POLE8B + 1300
#define Y_POLE8C Y_POLE8B




' pole 9 - kraj
#define X_POLE9 X_STD_POLE_PT5L
#define Y_POLE9 Y_POLE7 + Y_F_H_PT5L + Y_S_F_OFFSET_PT5L + 160

' pole 10 : wojewodztwo
#define X_POLE10 X_POLE9 + 4000
#define Y_POLE10 Y_POLE9

' pole 11 : powiat
#define X_POLE11 X_POLE10 + 8600
#define Y_POLE11 Y_POLE9

'pole 12 - gmina
#define X_POLE12 X_STD_POLE_PT5L
#define Y_POLE12 Y_POLE9 + Y_F_H_PT5L

' pole 13 : ulica
#define X_POLE13 X_POLE12 + 4950
#define Y_POLE13 Y_POLE12

' pole 14 : numer domu
#define X_POLE14 X_POLE13 + 9500
#define Y_POLE14 Y_POLE12

' pole 15 : numer lokalu
#define X_POLE15 X_POLE14 + 2100
#define Y_POLE15 Y_POLE12

'pole 16 - miejscowosc
#define X_POLE16 X_STD_POLE_PT5L
#define Y_POLE16 Y_POLE12 + Y_F_H_PT5L


' pole 17 : kod pocztowy
#define X_POLE17 X_POLE16 + 8400
#define Y_POLE17 Y_POLE16 

' pole 18 : poczta
#define X_POLE18 X_POLE17 + 3000
#define Y_POLE18 Y_POLE16



' SEKCJA C
#define Y_SC_OFFSET  Y_SB_OFFSET + Y_SB_H


#define X_POLE19 X_STD_POLE_PT5L + 8100 
#define Y_POLE19 Y_SC_OFFSET + 2280 + Y_S_F_T_OFFSET_PT4

#define X_COLUMN_SEC_C_WIDTH		3350

#define X_POLE20 X_POLE19 + X_COLUMN_SEC_C_WIDTH
#define Y_POLE20 Y_POLE19 


#define X_POLE21 X_POLE20 + X_COLUMN_SEC_C_WIDTH
#define Y_POLE21 Y_POLE20


#define X_POLE22 X_POLE21 + X_COLUMN_SEC_C_WIDTH
#define Y_POLE22 Y_POLE21



' SEKCJA D
#define Y_SD_OFFSET  Y_SC_OFFSET + 1700

#define X_POLE23 X_POLE22
#define Y_POLE23 Y_SD_OFFSET + 2300 + Y_S_F_T_OFFSET_PT4

#define X_POLE24 X_POLE23
#define Y_POLE24 Y_POLE23 + Y_F_H_PT5L


	

-->
<page backcolor='white' width='21000' height='29700' >
<config>
	<title>
Pit 5L - strona 1
#ifdef _DEBUG
[THIS_FILE]
#endif
</title>
<script><![CDATA[
<%
'funkcje pomocne przy ukladaniu napisów - do deklaracji
#include "50514" 

%>

]]></script>
</config>
<header>
</header>
<body>
<p width='X_PICTURE_WIDTH'>

<picture position='0,0' print='true'  scalingmode='1' image='PICTURE_BACKGROUND_PIT5L_1' width='X_PICTURE_WIDTH' height='Y_PICTURE_HEIGHT' />


<!--pole nr. 1  --> 
WTPFXY(1A,StretchDoKratki(left(replace(replace(root_.pt5l_strNIPPodatnik,"-","")," ",""),3)),PT5L_FONT_WYSOKOSC)
WTPFXY(1B,StretchDoKratki(mid(replace(replace(root_.pt5l_strNIPPodatnik,"-","")," ",""),4,3)),PT5L_FONT_WYSOKOSC)
WTPFXY(1C,StretchDoKratki(mid(replace(replace(root_.pt5l_strNIPPodatnik,"-","")," ",""),7,2)),PT5L_FONT_WYSOKOSC)
WTPFXY(1D,StretchDoKratki(mid(replace(replace(root_.pt5l_strNIPPodatnik,"-","")," ",""),9,2)),PT5L_FONT_WYSOKOSC)


<!-- pole 4 : miesiac --> 
WTPFXY(4A,StretchDoKratki(AlignRightPadd(CLng(month(root_.pt5l_dDataOd)),2,"0")),PT5L_FONT_WYSOKOSC)
WTPFXY(4B,StretchDoKratki(CStr(year(root_.pt5l_dDataOd))),PT5L_FONT_WYSOKOSC)

<!-- pole 5 : urząd skarbowy -->
WTPFXY(5,root_.pt5l_strUS,PT5L_FONT_WYSOKOSC)



<!-- B.1(pole 6) Nazwa pełna / nazwisko.... -->
WTPFXY(6,root_.pt5l_strNazwisko,PT5L_FONT_WYSOKOSC)

<!-- B.1(pole 7)  -->
WTPFXY(7,root_.pt5l_strImie,PT5L_FONT_WYSOKOSC)


WTPFXY(8A,StretchDoKratki(AlignRightPadd(CLng(day(root_.pt5l_dDataUr)),2,"0")),PIT11_FONT_WYSOKOSC)
WTPFXY(8B,StretchDoKratki(AlignRightPadd(CLng(month(root_.pt5l_dDataUr)),2,"0")),PIT11_FONT_WYSOKOSC)
WTPFXY(8C,StretchDoKratki(CStr(year(root_.pt5l_dDataUr))),PIT11_FONT_WYSOKOSC)







<!-- B.2( pole 9) Kraj -->
WTPFXY(9,root_.pt5l_strKraj,PT5L_FONT_WYSOKOSC)

<!-- B.2( pole 10) Województwo -->
WTPFXY(10,root_.pt5l_strWojewodztwo,PT5L_FONT_WYSOKOSC)

<!-- B.2( pole 11) Powiat -->
WTPFXY(11,root_.pt5l_strPowiat,PT5L_FONT_WYSOKOSC)


<!-- B.2( pole 12) Gmina -->
WTPFXY(12,root_.pt5l_strGmina,PT5L_FONT_WYSOKOSC)

<!-- B.2( pole 13) Ulica -->
WTPFXY(13,root_.pt5l_strUlica,PT5L_FONT_WYSOKOSC)

<!-- B.2( pole 14) Nr domu -->
WTPFXY(14,root_.pt5l_strNrDomu,PT5L_FONT_WYSOKOSC)

<!-- B.2( pole 15) Nr lokalu -->
WTPFXY(15,root_.pt5l_strNrLokalu,PT5L_FONT_WYSOKOSC)

<!-- B.2( pole 16) Miejscowość -->
WTPFXY(16,root_.pt5l_strMiejscowosc,PT5L_FONT_WYSOKOSC)

<!-- B.2( pole 17) Kod -->
WTPFXY(17,root_.pt5l_strKod,PT5L_FONT_WYSOKOSC)

<!-- B.2( pole 18) Poczta -->
WTPFXY(18,root_.pt5l_strPoczta,PT5L_FONT_WYSOKOSC)



<!-- pole 19 -->	PT5L_KWOTA(19,root_.pt5l_curPrzychod_DzialPozRol)
<!-- pole 20 -->	PT5L_KWOTA(20,root_.pt5l_curPrzychodKU_DzialPozRol)
<!-- pole 21 -->	PT5L_KWOTA(21,root_.pt5l_curDochod_DzialPozRol)
<!-- pole 22 -->	PT5L_KWOTA(22,root_.pt5l_curStrata_DzialPozRol)

<!-- pole 23 -->	PT5L_KWOTA(23,root_.pt5l_curStrata_PopLata)
<!-- pole 24 -->	PT5L_KWOTA(24,root_.pt5l_curSkladkaUbezSpol)



DEMO_MARKER(4000,11000)


</p>

</body>
<footer>
</footer>
</page>
