<?xml version="1.0" encoding="windows-1250" ?>
<!--
REV:KB:20030207

#include "h1000.h" 
#include "h1200.h" 
#include "h1229.h" 
-->
<class>
	<identifier>TYPEID_N5PLSKLWYN</identifier>
	<table>n5plsklwyn</table>
	<humanname>Składnik wynagrodzeń</humanname>
	<hidden/>
	<child/>
	<idobj/>

	XDF_PLACE_SKLADNIK_PARAM
<cursors />

<script>
<![CDATA[
function n5plsklwyn_as_text()
	n5plsklwyn_as_text = ""
end function

function n5plsklwyn_pSchemat_change(oldval)
	n5plsklwyn_pSchemat_change = true
	
	if not this_.pSchemat is nothing then
		this_.curParam1 = this_.pSchemat.curParam1
		this_.curParam2 = this_.pSchemat.curParam2
		set this_.pTerminNal = this_.pSchemat.pTerminNal
		this_.cConfParam1 = this_.pSchemat.cConfParam1
		this_.cConfParam2 = this_.pSchemat.cConfParam2
	end if

end function


function n5plsklwyn_copy_from (byref source)
	set this_.pSchemat = source.pSchemat
	this_.curParam1 = source.curParam1
	this_.curParam2 = source.curParam2
	set this_.pTerminNal = source.pTerminNal
	this_.cConfParam1 = source.cConfParam1
	this_.cConfParam2 = source.cConfParam2
end function

]]>
</script>
</class>
