<?xml version="1.0" encoding="windows-1250" ?>
<!--
Typ pracy


#include "h1000.h"
#include "h1001.h"
#include "h1201.h"
#include "h1203.h"
#include "h1219.h"
#include "h1220.h"
#include "h1230.h"
#include "h1231.h"
#include "h1240.h"
#include "h1222.h"
#include "h1200.h"
#include "h1232.h"
#include "h1228.h"

#define SECID_PODSTAWOWE			1002


#define FORM_SPAN					  4
#define RCELL_SPAN					  3

#define CTRLID_PRODUKT				101
-->

<page style='STYLE_PAGE'>

<config>
	<title>
Typ pracy
	#ifdef _DEBUG
	[THIS_FILE]
	#endif
	</title>
<typeid>TYPEID_N5PLTYPPRACY</typeid>
<script><![CDATA[
#include "50606"
#include "50200"

'HARUI_FREE
#include "50101"

function fopen(): fopen = true
#ifdef _ABAKUS
  fopen = not HARUI_FREE(UAR_OGRANICZONY_DOSTEP_DANE_KLIENTA)
#endif
end function

QVE_REF_OPEN_FORM(CTRLID_PRODUKT,tpr_pUsluga)

]]></script>
</config>
<header>
</header>
<body>

QXF_BEGIN
	QXS_BEGIN_FLAT(SECID_PODSTAWOWE,Informacje podstawowe,FORM_SPAN)
		QXR_EDIT_FIELD_REQ(Nazwa,-1,50,tpr_strNazwa,RCELL_SPAN)
		QXR_EDIT_FIELD_REQ(Kod,-1,10,tpr_strKod,RCELL_SPAN)
		QXR_PRICE_FIELD(Wynagrodzenie,-1,12,tpr_curWynagrodzenie,RCELL_SPAN)
		QXR_SEPARATOR(FORM_SPAN)
		QXX_EDIT_REF_PRODUKT(Produkt,CTRLID_PRODUKT,-1,40,tpr_pUsluga,CRSR_DEFAULT,RCELL_SPAN)
		QXX_CHOOSE_OPAKOWANIE(-1,Opakowanie,tpr_pOpak,tpr_pUsluga,RCELL_SPAN)
	QXS_END_FLAT(FORM_SPAN)
QXF_END


</body>
<footer>
</footer>
</page>
